Metadata-Version: 1.0
Name: seravo
Version: 0.0.0.dev20210714
Summary: Shared libraries for Seravo
Home-page: https://github.com/seravo/python-seravo/
Author: Seravo Oy
Author-email: help@seravo.com
License: UNKNOWN
Platform: UNKNOWN
